openad/__init__.py
openad/api.py
openad/app/__init__.py
openad/app/global_var_lib.py
openad/app/init_magic.py
openad/app/login_manager.py
openad/app/magic/__init__.py
openad/app/magic/openad_magic.py
openad/app/main.py
openad/app/main_lib.py
openad/app/memory.py
openad/app/metadata.json
openad/app/openad_examples.py
openad/app/params.json
openad/core/__init__.py
openad/core/grammar.py
openad/core/help.py
openad/core/lang_dev.py
openad/core/lang_file_system.py
openad/core/lang_runs.py
openad/core/lang_sessions_and_registry.py
openad/core/lang_workspaces.py
openad/docs_src/about_context.txt
openad/docs_src/about_mws.txt
openad/docs_src/about_plugin.txt
openad/docs_src/about_run.txt
openad/docs_src/about_workspace.txt
openad/docs_src/description.txt
openad/flask_apps/__init__.py
openad/flask_apps/_css/__init__.py
openad/flask_apps/_css/carbon.css
openad/flask_apps/_css/main.css
openad/flask_apps/_dev/arrow.svg
openad/flask_apps/_dev/caret.svg
openad/flask_apps/_js/carbon.js
openad/flask_apps/dataviewer/css/dataviewer-main.css
openad/flask_apps/dataviewer/css/tabulator_ibm_theme.css
openad/flask_apps/dataviewer/index.html
openad/flask_apps/dataviewer/js/context-menus.js
openad/flask_apps/dataviewer/js/dataviewer-main.js
openad/flask_apps/dataviewer/js/libs/luxon.min.js
openad/flask_apps/dataviewer/js/libs/moment.min.js
openad/flask_apps/dataviewer/js/table.js
openad/flask_apps/dataviewer/routes.py
openad/flask_apps/dataviewer/static/css/dataviewer-main.css
openad/flask_apps/dataviewer/static/css/tabulator_ibm_theme.css
openad/flask_apps/dataviewer/static/index.html
openad/flask_apps/dataviewer/static/js/context-menus.js
openad/flask_apps/dataviewer/static/js/dataviewer-main.js
openad/flask_apps/dataviewer/static/js/libs/luxon.min.js
openad/flask_apps/dataviewer/static/js/libs/moment.min.js
openad/flask_apps/dataviewer/static/js/moment.min.js
openad/flask_apps/dataviewer/static/js/table.js
openad/flask_apps/dataviewer/static/success.html
openad-0.8.0.dist-info/LICENSE
openad-0.8.0.dist-info/METADATA
openad-0.8.0.dist-info/WHEEL
openad-0.8.0.dist-info/entry_points.txt
openad-0.8.0.dist-info/RECORD
